[
  {
    "title": "", 
    "year":"", 
    "img":"", 
    "category": "", 
    "description": "", 
    "movie_link": "",
    "cast": [
      { 
        "actor_name": "String",
        "actor_photo": "String"
      }
    ]
  },
  {
    "title": "", 
    "year":"", 
    "img":"", 
    "category": "", 
    "description": "", 
    "movie_link": "",
    "cast": [
      { 
        "actor_name": "String",
        "actor_photo": "String"
      }
    ]
  },
  {
    "title": "", 
    "year":"", 
    "img":"", 
    "category": "", 
    "description": "", 
    "movie_link": "",
    "cast": [
      { 
        "actor_name": "String",
        "actor_photo": "String"
      }
    ]
  }
]